LICENSE.txt
MANIFEST.in
README.rst
setup.py
flask_objectid_converter/__init__.py
flask_objectid_converter.egg-info/PKG-INFO
flask_objectid_converter.egg-info/SOURCES.txt
flask_objectid_converter.egg-info/dependency_links.txt
flask_objectid_converter.egg-info/requires.txt
flask_objectid_converter.egg-info/top_level.txt