Metadata-Version: 1.1
Name: flask-objectid-converter
Version: 1.0.0
Summary: Provides url converters for flask to support pymonogs ObjectIDs
Home-page: https://github.com/Fischerfredl/flask-objectid-converter
Author: Alfred Melch
Author-email: alfred.melch@gmx.de
License: MIT
Keywords: flask,bson,pymongo,objectid,converter
Platform: UNKNOWN
Classifier: Framework :: Flask
Classifier: License :: OSI Approved :: MIT License
Classifier: Programming Language :: Python :: 2.7
Classifier: Programming Language :: Python :: 3.4
Classifier: Programming Language :: Python :: 3.5
Classifier: Programming Language :: Python :: 3.6
